fetch.py
webloader/__init__.py
webloader/constants.py
webloader/models.py
webloader/webloader.py
webloader-0.1.0.dist-info/LICENSE
webloader-0.1.0.dist-info/METADATA
webloader-0.1.0.dist-info/WHEEL
webloader-0.1.0.dist-info/entry_points.txt
webloader-0.1.0.dist-info/RECORD
