Metadata-Version: 2.1
Name: webloader
Version: 0.1.0
Summary: Python project fetching a webpage
License: LICENSE
Keywords: webloader
Author: Shubham Raj
Author-email: shubhamraj2202@gmail.com
Requires-Python: >=3.9,<4.0
Classifier: License :: Other/Proprietary License
Classifier: Programming Language :: Python :: 3
Classifier: Programming Language :: Python :: 3.9
Classifier: Programming Language :: Python :: 3.10
Classifier: Programming Language :: Python :: 3.11
Requires-Dist: bs4
Requires-Dist: pydantic
